openbci/__init__.py
openbci/cyton.py
openbci/ganglion.py
openbci/wifi.py
openbci/plugins/__init__.py
openbci/plugins/csv_collect.py
openbci/plugins/noise_test.py
openbci/plugins/print.py
openbci/plugins/sample_rate.py
openbci/plugins/streamer_lsl.py
openbci/plugins/streamer_osc.py
openbci/plugins/streamer_tcp_server.py
openbci/plugins/udp_server.py
openbci/utils/__init__.py
openbci/utils/constants.py
openbci/utils/parse.py
openbci/utils/ssdp.py
openbci/utils/utilities.py
OpenBCI_Python-1.0.2.dist-info/LICENSE
OpenBCI_Python-1.0.2.dist-info/METADATA
OpenBCI_Python-1.0.2.dist-info/WHEEL
OpenBCI_Python-1.0.2.dist-info/top_level.txt
OpenBCI_Python-1.0.2.dist-info/RECORD
